module_control_pkg/__init__.py
module_control_pkg/controllability.py
module_control_pkg/dominating_set.py
module_control_pkg/network_metrics.py
module_control_pkg/utils.py
module_control_pkg/visualize.py
module_control-0.2.0.dist-info/LICENSE
module_control-0.2.0.dist-info/METADATA
module_control-0.2.0.dist-info/WHEEL
module_control-0.2.0.dist-info/RECORD
